setup.py
CommonUtilities/MathUtils.py
CommonUtilities/__init__.py
CommonUtilities.egg-info/PKG-INFO
CommonUtilities.egg-info/SOURCES.txt
CommonUtilities.egg-info/dependency_links.txt
CommonUtilities.egg-info/not-zip-safe
CommonUtilities.egg-info/top_level.txt