Metadata-Version: 1.0
Name: CommonUtilities
Version: 0.1
Summary: Test...
Home-page: http://github.com/shankar-ray/CommonUtilities
Author: Sangram Kesari Ray
Author-email: shankar.ray030@gmail.com
License: MIT
Platform: UNKNOWN
